toolkey/__init__.py
toolkey/keys.py
toolkey-1.1.2.dist-info/METADATA
toolkey-1.1.2.dist-info/WHEEL
toolkey-1.1.2.dist-info/licenses/LICENSE.txt
toolkey-1.1.2.dist-info/RECORD
